[
  {
    "id": 1,
    "fullName": "Juan Fernandez",
    "age": 23,
    "cityCode": "MEX",
    "email": "jfer@email.com",
    "salary": 3500
  },
  {
    "id": 3,
    "fullName": "Phill Morris USA 123",
    "age": 37,
    "cityCode": "LAX",
    "email": "pmor@email.com",
    "salary": 6500
  },
  {
    "fullName": "Jorge Lopez",
    "age": 47,
    "cityCode": "HAB",
    "email": "doug@r3.com",
    "salary": 10000,
    "id": 5
  },
  {
    "id": 6,
    "fullName": "Jelo Hello",
    "age": 23,
    "cityCode": "HAB",
    "email": "d@d.com",
    "salary": 500
  }
]
